{"cameraMode":{"drawMode":0,"name":"Shaded","section":"Shading Mode"},"sceneLighting":false,"audioPlay":false,"sceneViewState":{"m_AlwaysRefresh":false,"showFog":true,"showSkybox":false,"showFlares":true,"showImageEffects":true,"showParticleSystems":true,"showVisualEffectGraphs":true,"m_FxEnabled":true},"in2DMode":false,"pivot":{"x":0.0772775411605835,"y":0.1441667079925537,"z":-0.2357020378112793},"rotation":{"x":0.16874277591705323,"y":-0.6021096706390381,"z":0.1321699023246765,"w":0.7691641449928284},"size":2.050100803375244,"orthographic":false}